Metadata-Version: 1.0
Name: pyhtml5ren
Version: 1.0.0
Summary: A way to render html in python/tk
Home-page: UNKNOWN
Author: UNKNOWN
Author-email: UNKNOWN
License: UNKNOWN
Platform: UNKNOWN
